MANIFEST.in
README.rst
setup.py
django_cms_smartsnippets.egg-info/PKG-INFO
django_cms_smartsnippets.egg-info/SOURCES.txt
django_cms_smartsnippets.egg-info/dependency_links.txt
django_cms_smartsnippets.egg-info/top_level.txt
smartsnippets/__init__.py
smartsnippets/admin.py
smartsnippets/cms_plugins.py
smartsnippets/models.py
smartsnippets/settings.py
smartsnippets/tests.py
smartsnippets/views.py
smartsnippets/migrations/0001_initial.py
smartsnippets/migrations/0002_auto.py
smartsnippets/migrations/0003_auto__add_field_smartsnippet_template_path.py
smartsnippets/migrations/0004_auto__chg_field_smartsnippet_template_path.py
smartsnippets/migrations/__init__.py
smartsnippets/templates/smartsnippets/base.html
smartsnippets/templates/smartsnippets/base_site.html
smartsnippets/templates/smartsnippets/change_form.html
smartsnippets/templates/smartsnippets/fieldset.html
smartsnippets/templates/smartsnippets/plugin.html
smartsnippets/templates/smartsnippets/plugin_change_form.html
smartsnippets/templates/smartsnippets/snippet_change_form.html