Metadata-Version: 1.0
Name: django-cms-smartsnippets
Version: 0.1.3
Summary: Parametrizable Django CMS snippets.
Home-page: UNKNOWN
Author: Sever Banesiu
Author-email: banesiu.sever@gmail.com
License: BSD License
Platform: UNKNOWN
